minitap/mobile_use/__init__.py
minitap/mobile_use/agents/contextor/contextor.md
minitap/mobile_use/agents/contextor/contextor.py
minitap/mobile_use/agents/contextor/types.py
minitap/mobile_use/agents/cortex/cortex.md
minitap/mobile_use/agents/cortex/cortex.py
minitap/mobile_use/agents/cortex/types.py
minitap/mobile_use/agents/executor/executor.md
minitap/mobile_use/agents/executor/executor.py
minitap/mobile_use/agents/executor/tool_node.py
minitap/mobile_use/agents/hopper/hopper.md
minitap/mobile_use/agents/hopper/hopper.py
minitap/mobile_use/agents/orchestrator/human.md
minitap/mobile_use/agents/orchestrator/orchestrator.md
minitap/mobile_use/agents/orchestrator/orchestrator.py
minitap/mobile_use/agents/orchestrator/types.py
minitap/mobile_use/agents/outputter/human.md
minitap/mobile_use/agents/outputter/outputter.py
minitap/mobile_use/agents/outputter/test_outputter.py
minitap/mobile_use/agents/planner/human.md
minitap/mobile_use/agents/planner/planner.md
minitap/mobile_use/agents/planner/planner.py
minitap/mobile_use/agents/planner/types.py
minitap/mobile_use/agents/planner/utils.py
minitap/mobile_use/agents/summarizer/summarizer.py
minitap/mobile_use/agents/video_analyzer/__init__.py
minitap/mobile_use/agents/video_analyzer/human.md
minitap/mobile_use/agents/video_analyzer/video_analyzer.md
minitap/mobile_use/agents/video_analyzer/video_analyzer.py
minitap/mobile_use/clients/browserstack_client.py
minitap/mobile_use/clients/idb_client.py
minitap/mobile_use/clients/ios_client.py
minitap/mobile_use/clients/ios_client_config.py
minitap/mobile_use/clients/ui_automator_client.py
minitap/mobile_use/clients/wda_client.py
minitap/mobile_use/clients/wda_lifecycle.py
minitap/mobile_use/config.py
minitap/mobile_use/constants.py
minitap/mobile_use/context.py
minitap/mobile_use/controllers/__init__.py
minitap/mobile_use/controllers/android_controller.py
minitap/mobile_use/controllers/controller_factory.py
minitap/mobile_use/controllers/device_controller.py
minitap_mobile_use-3.4.0.dist-info/WHEEL
minitap_mobile_use-3.4.0.dist-info/entry_points.txt
minitap_mobile_use-3.4.0.dist-info/METADATA
minitap_mobile_use-3.4.0.dist-info/RECORD
