Metadata-Version: 2.3
Name: minitap-mobile-use
Version: 3.4.0
Summary: AI-powered multi-agent system that automates real Android and iOS devices through low-level control using LangGraph.
Author: Pierre-Louis Favreau, Jean-Pierre Lo, Nicolas Dehandschoewercker
License:                                  Apache License
Requires-Dist: langgraph>=1.0.0
Requires-Dist: adbutils==2.9.3
Requires-Dist: langchain-google-genai>=2.1.10
Requires-Dist: langchain>=0.3.27
Requires-Dist: langchain-core>=0.3.75
Requires-Dist: jinja2==3.1.6
Requires-Dist: python-dotenv==1.1.1
Requires-Dist: pydantic-settings==2.10.1
Requires-Dist: langchain-mcp-adapters==0.1.7
Requires-Dist: langchain-openai==0.3.27
Requires-Dist: typer==0.16.0
Requires-Dist: langchain-cerebras>=0.5.0
Requires-Dist: inquirer>=3.4.0
Requires-Dist: sseclient-py==1.8.0
Requires-Dist: fastapi==0.111.0
Requires-Dist: uvicorn[standard]==0.30.1
Requires-Dist: colorama>=0.4.6
Requires-Dist: psutil>=5.9.0
Requires-Dist: langchain-google-vertexai>=2.0.28
Requires-Dist: httpx>=0.28.1
Requires-Dist: uiautomator2>=3.5.0
Requires-Dist: fb-idb==1.1.7
Requires-Dist: facebook-wda>=1.5.4
Requires-Dist: appium-python-client>=5.0.0
Requires-Dist: posthog>=7.4.2
Requires-Dist: uuid-utils>=0.12.0
Requires-Dist: ruff==0.5.3 ; extra == 'dev'
Requires-Dist: pytest==8.4.1 ; extra == 'dev'
Requires-Dist: pytest-cov==5.0.0 ; extra == 'dev'
Requires-Dist: pyright==1.1.405 ; extra == 'dev'
Requires-Python: >=3.12
Project-URL: Homepage, https://minitap.ai/
Project-URL: Source, https://github.com/minitap-ai/mobile-use
Provides-Extra: dev
